chemplus/__init__.py
chemplus/draw.py
chemplus/mdl.py
chemplus/mol_df.py
chemplus/sdf.py
chemplus/hpc/__init__.py
chemplus/hpc/docking_parser.py
chemplus/hpc/hpc_docking.py
chemplus/hpc/ucc.py
chemplus/hpc/files/docking.u
chemplus/pymol/__init__.py
chemplus/vina/__init__.py
chemplus/vina/docking.py
chemplus/vina/docking_mpi.py
chemplus/vina/dockscore.py
chemplus/vina/exprank.py
chemplus/vina/pdbqt.py
chemplus/vina/pdbqt_to_sdf.py
chemplus/vina/rot_bond_helper.py
chemplus/vina/scripts/prepare_ligand4.py
chemplus/vina/sf/autodock_vina/LICENSE
chemplus/vina/sf/autodock_vina/vina
chemplus/vina/sf/autodock_vina/vina.exe
chemplus/vina/sf/autodock_vina/vina_license.rtf
chemplus/vina/sf/nnscore2.0/CONTRIBUTORS.md
chemplus/vina/sf/nnscore2.0/NNScore2.py
chemplus/vina/sf/nnscore2.0/gpl-3.0.txt
chemplus/vina/sf/rfscore4/LICENSE
chemplus/vina/sf/rfscore4/pdbbind-2014-refined.rf
chemplus/vina/sf/rfscore4/rf-score
chemplus/vina/sf/rfscore4/rf-score.exe
chemplus-0.0.2.dist-info/METADATA
chemplus-0.0.2.dist-info/WHEEL
chemplus-0.0.2.dist-info/licenses/LICENSE
chemplus-0.0.2.dist-info/RECORD
