Metadata-Version: 2.1
Name: chemplus
Version: 0.0.2
Summary: The chemical toolkit for drug discovery
Project-URL: Homepage, https://github.com/Deep-Drug/chemplus
Project-URL: Bug Tracker, https://github.com/Deep-Drug/chemplus/issues
Author-email: Drug Design Group BY <designdrug.by@gmail.com>
License: GPLv3
License-File: LICENSE
Classifier: License :: OSI Approved :: GNU General Public License v3 (GPLv3)
Classifier: Operating System :: OS Independent
Classifier: Programming Language :: Python :: 3
Requires-Python: >=3.9
Requires-Dist: mpi4py>=3.1.3
Requires-Dist: rdkit>=2021.09.2
Requires-Dist: tqdm>=4.62.3
